scrap.py
scrapso.py
scrap_stackoverflow-0.0.1.dist-info/LICENSE
scrap_stackoverflow-0.0.1.dist-info/METADATA
scrap_stackoverflow-0.0.1.dist-info/WHEEL
scrap_stackoverflow-0.0.1.dist-info/top_level.txt
scrap_stackoverflow-0.0.1.dist-info/RECORD
