Metadata-Version: 2.1
Name: scrap-stackoverflow
Version: 0.0.1
Summary: A package to scrap Stackoverflow website
Home-page: https://github.com/komus/stackoverflow-classification/tree/pypi_scrapping
Author: Oyindolapo Komolafe
Author-email: oyindolapokomolafe@yahoo.com
License: UNKNOWN
Platform: UNKNOWN
Classifier: Programming Language :: Python :: 3
Classifier: Programming Language :: Python :: 3.8
Classifier: Programming Language :: Python :: 3.9
Classifier: License :: OSI Approved :: GNU Lesser General Public License v3 (LGPLv3)
Classifier: Operating System :: OS Independent
License-File: LICENSE
Requires-Dist: beautifulsoup4 (~=4.9.3)
Requires-Dist: requests (~=2.25.1)
Requires-Dist: pandas (~=1.3.0)
Provides-Extra: dev
Requires-Dist: pytest (>=3.7) ; extra == 'dev'
